dqcsim_cqasm-0.0.3.dist-info/METADATA
dqcsim_cqasm-0.0.3.dist-info/RECORD
dqcsim_cqasm-0.0.3.dist-info/WHEEL
dqcsim_cqasm-0.0.3.dist-info/top_level.txt
dqcsim_cqasm-0.0.3.data/data/bin/dqcsfecq
dqcsim_cqasm-0.0.3.data/purelib/dqcsim_cqasm/test.py
dqcsim_cqasm-0.0.3.data/purelib/dqcsim_cqasm/__init__.py
