Metadata-Version: 2.1
Name: dqcsim-cqasm
Version: 0.0.3
Summary: A DQCsim frontend for cQASM files
Home-page: https://github.com/QE-Lab/dqcsim-cqasm
Author: Quantum Computer Architectures, Quantum & Computer Engineering, QuTech, Delft University of Technology
Author-email: 
License: Apache-2.0
Project-URL: Source Code, https://github.com/QE-Lab/dqcsim-cqasm
Platform: UNKNOWN
Classifier: License :: OSI Approved :: Apache Software License
Classifier: Operating System :: POSIX :: Linux
Classifier: Programming Language :: C
Classifier: Programming Language :: C++
Classifier: Topic :: Scientific/Engineering
Requires-Dist: dqcsim
